qtealeaves/__init__.py
qtealeaves/version.py
qtealeaves/abstracttns/__init__.py
qtealeaves/abstracttns/abstract_matrix_tn.py
qtealeaves/abstracttns/abstract_tn.py
qtealeaves/abstracttns/checks_abstract_tn_ml.py
qtealeaves/convergence_parameters/__init__.py
qtealeaves/convergence_parameters/conv_params.py
qtealeaves/convergence_parameters/conv_params_finite_temp.py
qtealeaves/emulator/__init__.py
qtealeaves/emulator/attn_simulator.py
qtealeaves/emulator/lptn_simulator.py
qtealeaves/emulator/mpi_mps_simulator.py
qtealeaves/emulator/mps_simulator.py
qtealeaves/emulator/state_simulator.py
qtealeaves/emulator/tnnode.py
qtealeaves/emulator/ttn_simulator.py
qtealeaves/emulator/tto_simulator.py
qtealeaves/emulator/unitariesprojmeas.py
qtealeaves/modeling/__init__.py
qtealeaves/modeling/baseterm.py
qtealeaves/modeling/blockterm2d.py
qtealeaves/modeling/custom_site_term.py
qtealeaves/modeling/localterm.py
qtealeaves/modeling/plaquetteterm2d.py
qtealeaves/modeling/quantummodel.py
qtealeaves/modeling/stringterm1d.py
qtealeaves/modeling/sumlocalterm.py
qtealeaves/modeling/twobodyterm1d.py
qtealeaves/modeling/twobodyterm2d.py
qtealeaves/modeling/twobodyterm3d.py
qtealeaves/models/__init__.py
qtealeaves/models/bosehubbard.py
qtealeaves/models/quantumising.py
qtealeaves/models/singletfission.py
qtealeaves/models/spin1_xyz.py
qtealeaves/models/xxzmodel.py
qtealeaves/mpos/__init__.py
qtealeaves/mpos/abstracteffop.py
qtealeaves/mpos/densempos.py
qtealeaves/mpos/disentangler.py
qtealeaves/mpos/indexedtpo.py
qtealeaves/mpos/mldatampo.py
qtealeaves/mpos/mps_projector.py
qtealeaves/mpos/sparsematrixoperator.py
qtealeaves/mpos/sparsematrixproductoperator.py
qtealeaves/mpos/ttn_projector.py
qtealeaves/observables/__init__.py
qtealeaves/observables/bond_entropy.py
qtealeaves/observables/checks_tnobservables.py
qtealeaves/observables/correlation.py
qtealeaves/observables/custom_correlation.py
qtealeaves/observables/custom_function_obs.py
qtealeaves/observables/distance2pure.py
qtealeaves-1.7.21.dist-info/licenses/LICENSE
qtealeaves-1.7.21.dist-info/METADATA
qtealeaves-1.7.21.dist-info/WHEEL
qtealeaves-1.7.21.dist-info/top_level.txt
qtealeaves-1.7.21.dist-info/RECORD
