Metadata-Version: 2.4
Name: qtealeaves
Version: 1.7.21
Summary: Quantum TEA's python tensor network library
Home-page: https://baltig.infn.it/quantum_tea_leaves/py_api_quantum_tea_leaves.git
Author: Flavio Baccari, Davide Bacilieri, Marco Ballarin, Francesco Pio Barone, Francesco Campaioli, Alberto Giuseppe Catalano, Giovanni Cataldi, Massimo Colombo, Alberto Coppi, Aurora Costantini, Asmita Datta, Andrea De Girolamo, Daniel Jaschke, Sven Benjamin Kožić, Giuseppe Magnifico, Madhav Menon, Carmelo Mordini, Guillermo Muñoz Menés, Simone Notarnicola, Alice Pagano, Luka Pavesic, Davide Rattacaso, Nora Reinić, Marco Rigobello, Simone Scarlatella, Ilaria Siloi, Marco Tesoro, Gianpaolo Torr
Author-email: quantumtea@lists.infn.it
Classifier: Programming Language :: Python :: 3
Classifier: Operating System :: OS Independent
Requires-Python: >=3.11
License-File: LICENSE
Requires-Dist: numpy>=1.26.0
Requires-Dist: scipy
Requires-Dist: matplotlib
Requires-Dist: mpmath
Requires-Dist: joblib
Requires-Dist: h5py
Dynamic: author
Dynamic: author-email
Dynamic: classifier
Dynamic: description
Dynamic: description-content-type
Dynamic: home-page
Dynamic: license-file
Dynamic: requires-dist
Dynamic: requires-python
Dynamic: summary
